{"symbol": "PVI", "days": 120, "date": "2026-02-11", "timestamp": "2026-02-11T22:00:36.084049", "rows": 89, "data": [{"time": "2025-10-08", "open": 68.0, "high": 69.0, "low": 68.0, "close": 68.9, "volume": 10971}, {"time": "2025-10-09", "open": 68.8, "high": 69.2, "low": 68.0, "close": 69.2, "volume": 31089}, {"time": "2025-10-10", "open": 70.6, "high": 70.6, "low": 69.2, "close": 69.5, "volume": 41109}, {"time": "2025-10-13", "open": 69.5, "high": 69.5, "low": 68.1, "close": 68.1, "volume": 10596}, {"time": "2025-10-14", "open": 68.1, "high": 69.6, "low": 68.1, "close": 68.2, "volume": 15200}, {"time": "2025-10-15", "open": 67.0, "high": 68.5, "low": 67.0, "close": 68.5, "volume": 2900}, {"time": "2025-10-16", "open": 67.7, "high": 68.3, "low": 67.4, "close": 68.3, "volume": 16900}, {"time": "2025-10-17", "open": 68.3, "high": 68.3, "low": 67.5, "close": 67.8, "volume": 8000}, {"time": "2025-10-20", "open": 67.0, "high": 67.5, "low": 66.0, "close": 66.0, "volume": 21500}, {"time": "2025-10-21", "open": 66.0, "high": 66.0, "low": 65.5, "close": 65.6, "volume": 23100}, {"time": "2025-10-22", "open": 71.9, "high": 71.9, "low": 66.4, "close": 68.2, "volume": 9100}, {"time": "2025-10-23", "open": 70.0, "high": 73.5, "low": 70.0, "close": 73.2, "volume": 149800}, {"time": "2025-10-24", "open": 75.0, "high": 75.0, "low": 72.2, "close": 73.5, "volume": 41800}, {"time": "2025-10-27", "open": 73.4, "high": 74.5, "low": 70.3, "close": 73.0, "volume": 17600}, {"time": "2025-10-28", "open": 71.1, "high": 72.5, "low": 71.1, "close": 72.5, "volume": 48500}, {"time": "2025-10-29", "open": 71.2, "high": 72.1, "low": 70.6, "close": 71.4, "volume": 46600}, {"time": "2025-10-30", "open": 72.4, "high": 73.0, "low": 71.2, "close": 72.3, "volume": 42200}, {"time": "2025-10-31", "open": 72.3, "high": 73.9, "low": 71.7, "close": 73.9, "volume": 147300}, {"time": "2025-11-03", "open": 75.0, "high": 81.2, "low": 74.8, "close": 81.0, "volume": 408900}, {"time": "2025-11-04", "open": 81.1, "high": 81.2, "low": 79.0, "close": 80.8, "volume": 50100}, {"time": "2025-11-05", "open": 80.8, "high": 80.8, "low": 78.7, "close": 78.8, "volume": 43100}, {"time": "2025-11-06", "open": 76.2, "high": 80.9, "low": 76.2, "close": 79.4, "volume": 20700}, {"time": "2025-11-07", "open": 78.8, "high": 79.0, "low": 77.0, "close": 79.0, "volume": 29300}, {"time": "2025-11-10", "open": 78.8, "high": 80.0, "low": 75.0, "close": 78.0, "volume": 101200}, {"time": "2025-11-11", "open": 78.0, "high": 85.0, "low": 78.0, "close": 84.9, "volume": 62400}, {"time": "2025-11-12", "open": 85.0, "high": 90.2, "low": 84.0, "close": 86.4, "volume": 88700}, {"time": "2025-11-13", "open": 86.2, "high": 88.0, "low": 85.8, "close": 86.8, "volume": 54600}, {"time": "2025-11-14", "open": 86.0, "high": 92.0, "low": 86.0, "close": 90.0, "volume": 81000}, {"time": "2025-11-17", "open": 90.0, "high": 90.5, "low": 86.8, "close": 86.8, "volume": 84700}, {"time": "2025-11-18", "open": 86.8, "high": 92.0, "low": 85.8, "close": 90.4, "volume": 128300}, {"time": "2025-11-19", "open": 90.2, "high": 90.4, "low": 87.1, "close": 89.0, "volume": 73700}, {"time": "2025-11-20", "open": 90.0, "high": 92.0, "low": 88.2, "close": 89.9, "volume": 36600}, {"time": "2025-11-21", "open": 90.2, "high": 90.5, "low": 88.2, "close": 90.0, "volume": 69700}, {"time": "2025-11-24", "open": 90.0, "high": 91.7, "low": 90.0, "close": 90.2, "volume": 78300}, {"time": "2025-11-25", "open": 87.0, "high": 90.4, "low": 86.0, "close": 86.6, "volume": 86200}, {"time": "2025-11-26", "open": 86.3, "high": 89.9, "low": 86.3, "close": 87.5, "volume": 71600}, {"time": "2025-11-27", "open": 87.8, "high": 89.0, "low": 86.5, "close": 87.1, "volume": 19300}, {"time": "2025-11-28", "open": 87.4, "high": 89.0, "low": 87.1, "close": 87.8, "volume": 35000}, {"time": "2025-12-01", "open": 89.7, "high": 90.0, "low": 87.5, "close": 88.0, "volume": 69600}, {"time": "2025-12-02", "open": 87.3, "high": 88.8, "low": 87.3, "close": 87.8, "volume": 106800}, {"time": "2025-12-03", "open": 87.8, "high": 90.4, "low": 87.6, "close": 87.6, "volume": 109400}, {"time": "2025-12-04", "open": 89.0, "high": 89.5, "low": 88.2, "close": 88.3, "volume": 71400}, {"time": "2025-12-05", "open": 89.0, "high": 97.1, "low": 89.0, "close": 97.1, "volume": 190200}, {"time": "2025-12-08", "open": 100.0, "high": 106.8, "low": 98.0, "close": 101.8, "volume": 199900}, {"time": "2025-12-09", "open": 102.1, "high": 102.9, "low": 96.5, "close": 97.8, "volume": 83800}, {"time": "2025-12-10", "open": 101.2, "high": 102.5, "low": 94.8, "close": 94.8, "volume": 88100}, {"time": "2025-12-11", "open": 86.2, "high": 96.9, "low": 86.2, "close": 94.8, "volume": 48400}, {"time": "2025-12-12", "open": 95.0, "high": 95.0, "low": 88.6, "close": 89.0, "volume": 101300}, {"time": "2025-12-15", "open": 89.0, "high": 92.4, "low": 86.0, "close": 86.7, "volume": 85200}, {"time": "2025-12-16", "open": 86.4, "high": 90.6, "low": 86.3, "close": 88.0, "volume": 172100}, {"time": "2025-12-17", "open": 88.1, "high": 90.0, "low": 88.1, "close": 89.5, "volume": 68400}, {"time": "2025-12-18", "open": 90.4, "high": 93.4, "low": 90.0, "close": 91.6, "volume": 80300}, {"time": "2025-12-19", "open": 91.8, "high": 92.9, "low": 90.5, "close": 92.5, "volume": 98700}, {"time": "2025-12-22", "open": 92.5, "high": 92.5, "low": 91.3, "close": 91.9, "volume": 25100}, {"time": "2025-12-23", "open": 87.2, "high": 95.0, "low": 87.2, "close": 89.3, "volume": 63900}, {"time": "2025-12-24", "open": 89.0, "high": 89.3, "low": 87.9, "close": 88.0, "volume": 53900}, {"time": "2025-12-25", "open": 88.0, "high": 88.9, "low": 86.0, "close": 86.0, "volume": 82400}, {"time": "2025-12-26", "open": 85.9, "high": 94.6, "low": 82.1, "close": 94.6, "volume": 566700}, {"time": "2025-12-29", "open": 95.2, "high": 104.0, "low": 95.0, "close": 97.0, "volume": 254100}, {"time": "2025-12-30", "open": 103.0, "high": 103.0, "low": 95.1, "close": 96.8, "volume": 246400}, {"time": "2025-12-31", "open": 97.1, "high": 99.9, "low": 93.0, "close": 93.0, "volume": 117000}, {"time": "2026-01-05", "open": 96.4, "high": 98.8, "low": 95.0, "close": 95.0, "volume": 63600}, {"time": "2026-01-06", "open": 94.0, "high": 99.0, "low": 94.0, "close": 97.9, "volume": 424300}, {"time": "2026-01-07", "open": 98.2, "high": 99.0, "low": 97.5, "close": 98.5, "volume": 129900}, {"time": "2026-01-08", "open": 97.3, "high": 99.0, "low": 95.8, "close": 96.0, "volume": 62200}, {"time": "2026-01-09", "open": 97.9, "high": 97.9, "low": 93.3, "close": 93.5, "volume": 78700}, {"time": "2026-01-12", "open": 93.5, "high": 99.0, "low": 93.3, "close": 93.5, "volume": 95500}, {"time": "2026-01-13", "open": 94.5, "high": 94.5, "low": 92.4, "close": 93.0, "volume": 62000}, {"time": "2026-01-14", "open": 93.0, "high": 96.9, "low": 91.6, "close": 93.0, "volume": 132500}, {"time": "2026-01-15", "open": 93.0, "high": 102.3, "low": 93.0, "close": 102.3, "volume": 644600}, {"time": "2026-01-16", "open": 111.8, "high": 112.5, "low": 108.0, "close": 112.5, "volume": 971600}, {"time": "2026-01-19", "open": 123.7, "high": 123.7, "low": 102.0, "close": 105.8, "volume": 490300}, {"time": "2026-01-20", "open": 106.0, "high": 112.0, "low": 100.0, "close": 100.0, "volume": 459300}, {"time": "2026-01-21", "open": 100.0, "high": 104.0, "low": 95.0, "close": 101.3, "volume": 130400}, {"time": "2026-01-22", "open": 101.3, "high": 101.3, "low": 94.0, "close": 95.0, "volume": 303100}, {"time": "2026-01-23", "open": 90.0, "high": 95.2, "low": 90.0, "close": 90.0, "volume": 186700}, {"time": "2026-01-26", "open": 90.0, "high": 93.8, "low": 86.1, "close": 86.1, "volume": 223600}, {"time": "2026-01-27", "open": 87.0, "high": 91.9, "low": 86.0, "close": 90.4, "volume": 107900}, {"time": "2026-01-28", "open": 88.0, "high": 91.8, "low": 86.0, "close": 89.4, "volume": 78600}, {"time": "2026-01-29", "open": 90.7, "high": 90.7, "low": 86.0, "close": 86.5, "volume": 141500}, {"time": "2026-01-30", "open": 90.8, "high": 90.8, "low": 86.2, "close": 86.4, "volume": 70400}, {"time": "2026-02-02", "open": 86.5, "high": 88.8, "low": 83.6, "close": 88.2, "volume": 162100}, {"time": "2026-02-03", "open": 88.2, "high": 91.9, "low": 86.6, "close": 91.5, "volume": 185000}, {"time": "2026-02-04", "open": 91.8, "high": 100.5, "low": 91.5, "close": 95.4, "volume": 216500}, {"time": "2026-02-05", "open": 95.4, "high": 95.4, "low": 92.8, "close": 92.8, "volume": 110600}, {"time": "2026-02-06", "open": 91.5, "high": 91.5, "low": 85.1, "close": 87.0, "volume": 84800}, {"time": "2026-02-09", "open": 88.0, "high": 89.4, "low": 86.3, "close": 87.5, "volume": 47300}, {"time": "2026-02-10", "open": 89.4, "high": 89.4, "low": 85.9, "close": 86.0, "volume": 43700}, {"time": "2026-02-11", "open": 86.0, "high": 88.5, "low": 86.0, "close": 86.9, "volume": 83600}]}