{
  "timestamp": "2025-12-11T11:40:00.027523",
  "data": [
    {
      "period": "Q1",
      "revenue": 121543602398.0,
      "profit": 107827824130.0,
      "eps": 0.0,
      "roe": -85.09784046,
      "roa": -16.39961935,
      "gross_margin": 0.0,
      "net_margin": 0.0
    },
    {
      "period": "Q2",
      "revenue": 3479199645.0,
      "profit": -104509778840.0,
      "eps": 0.0,
      "roe": -82.9276279,
      "roa": -19.00981363,
      "gross_margin": 0.0,
      "net_margin": 0.0
    },
    {
      "period": "Q3",
      "revenue": 77158113981.0,
      "profit": 12280655368.0,
      "eps": 0.0,
      "roe": -78.21946487,
      "roa": -21.16650233,
      "gross_margin": 0.0,
      "net_margin": 0.0
    },
    {
      "period": "Q4",
      "revenue": 1341742727.0,
      "profit": -1032525524786.0,
      "eps": 0.0,
      "roe": -76.72597007,
      "roa": -22.43595733,
      "gross_margin": 0.0,
      "net_margin": 0.0
    },
    {
      "period": "Q5",
      "revenue": -25188411350.0,
      "profit": -77066264320.0,
      "eps": 0.0,
      "roe": -25.47293993,
      "roa": -9.07441297,
      "gross_margin": 0.0,
      "net_margin": 0.0
    },
    {
      "period": "Q6",
      "revenue": -19217396422.0,
      "profit": -271291636838.0,
      "eps": 0.0,
      "roe": -23.16821629,
      "roa": -8.64480627,
      "gross_margin": 0.0,
      "net_margin": 0.0
    },
    {
      "period": "Q7",
      "revenue": -130169215071.0,
      "profit": -124868454236.0,
      "eps": 0.0,
      "roe": -14.81775293,
      "roa": -5.70239982,
      "gross_margin": 0.0,
      "net_margin": 0.0
    },
    {
      "period": "Q8",
      "revenue": -36994614365.0,
      "profit": -165077519284.0,
      "eps": 0.0,
      "roe": -17.702733000000002,
      "roa": -6.97032586,
      "gross_margin": 0.0,
      "net_margin": 0.0
    },
    {
      "period": "Q9",
      "revenue": -554744801.0,
      "profit": -64979475194.0,
      "eps": 0.0,
      "roe": -7.89666991,
      "roa": -3.17365337,
      "gross_margin": 0.0,
      "net_margin": 0.0
    },
    {
      "period": "Q10",
      "revenue": 330527811.0,
      "profit": -74365426749.0,
      "eps": 0.0,
      "roe": -5.52757758,
      "roa": -2.25226753,
      "gross_margin": 0.0,
      "net_margin": 0.0
    },
    {
      "period": "Q11",
      "revenue": 709807273.0,
      "profit": -69983982132.0,
      "eps": 0.0,
      "roe": -2.0947956100000003,
      "roa": -0.86903239,
      "gross_margin": 0.0,
      "net_margin": 0.0
    },
    {
      "period": "Q12",
      "revenue": 46824783231.0,
      "profit": -38881135283.0,
      "eps": 0.0,
      "roe": 0.12301268000000001,
      "roa": 0.05426371000000001,
      "gross_margin": 0.0,
      "net_margin": 0.0
    },
    {
      "period": "Q13",
      "revenue": 6830987919.0,
      "profit": 5666690477.0,
      "eps": 0.0,
      "roe": 4.63374405,
      "roa": 2.0546721,
      "gross_margin": 0.0,
      "net_margin": 0.0
    },
    {
      "period": "Q14",
      "revenue": 96079137097.0,
      "profit": 34820359324.0,
      "eps": 0.0,
      "roe": 5.47083526,
      "roa": 2.48666272,
      "gross_margin": 0.0,
      "net_margin": 0.0
    },
    {
      "period": "Q15",
      "revenue": 126567526341.0,
      "profit": 2401737410.0,
      "eps": 0.0,
      "roe": 4.48546893,
      "roa": 2.1062534,
      "gross_margin": 0.0,
      "net_margin": 0.0
    },
    {
      "period": "Q16",
      "revenue": 69757821072.0,
      "profit": 108912579594.0,
      "eps": 0.0,
      "roe": 4.4311702,
      "roa": 2.27358246,
      "gross_margin": 0.0,
      "net_margin": 0.0
    },
    {
      "period": "Q17",
      "revenue": 124180970229.0,
      "profit": 30716696713.0,
      "eps": 0.0,
      "roe": 1.03071946,
      "roa": 0.52194877,
      "gross_margin": 0.0,
      "net_margin": 0.0
    },
    {
      "period": "Q18",
      "revenue": 90327147670.0,
      "profit": 715379059.0,
      "eps": 0.0,
      "roe": 0.37218236000000005,
      "roa": 0.20010980000000003,
      "gross_margin": 0.0,
      "net_margin": 0.0
    },
    {
      "period": "Q19",
      "revenue": 37016064943.0,
      "profit": 307942462.0,
      "eps": 0.0,
      "roe": 0.38175045046955347,
      "roa": 0.2113930182531476,
      "gross_margin": 0.0,
      "net_margin": 0.0
    },
    {
      "period": "Q20",
      "revenue": 197329043713.0,
      "profit": 337367015.0,
      "eps": 0.0,
      "roe": 0.41460244,
      "roa": 0.22687728,
      "gross_margin": 0.0,
      "net_margin": 0.0
    }
  ]
}