{
  "symbol": "TDH",
  "last_updated": "2026-02-11T22:53:01.496697",
  "count": 30,
  "snapshots": [
    {
      "date": "2025-12-31",
      "symbol": "TDH",
      "open": 4.43,
      "high": 4.43,
      "low": 4.24,
      "close": 4.37,
      "volume": 31100,
      "change_pct": -0.22831050228310223,
      "ma20": 4.483,
      "ma50": 4.7008,
      "ma200": 4.7008,
      "rsi_14": 27.08333333333333,
      "macd": 0.0,
      "macd_signal": 0.0,
      "macd_histogram": 0.0,
      "volume_ma20": 131910.0,
      "volume_ratio": 0.23576681070426805,
      "poc": 0.0,
      "vah": 0.0,
      "val": 0.0,
      "rs_rating": 50
    },
    {
      "date": "2026-01-05",
      "symbol": "TDH",
      "open": 4.08,
      "high": 4.34,
      "low": 4.08,
      "close": 4.34,
      "volume": 190500,
      "change_pct": -0.6864988558352492,
      "ma20": 4.463,
      "ma50": 4.687600000000001,
      "ma200": 4.687600000000001,
      "rsi_14": 37.14285714285714,
      "macd": 0.0,
      "macd_signal": 0.0,
      "macd_histogram": 0.0,
      "volume_ma20": 133900.0,
      "volume_ratio": 1.4227035100821508,
      "poc": 0.0,
      "vah": 0.0,
      "val": 0.0,
      "rs_rating": 50
    },
    {
      "date": "2026-01-06",
      "symbol": "TDH",
      "open": 4.37,
      "high": 4.37,
      "low": 4.2,
      "close": 4.27,
      "volume": 60500,
      "change_pct": -1.6129032258064613,
      "ma20": 4.4399999999999995,
      "ma50": 4.675000000000001,
      "ma200": 4.675000000000001,
      "rsi_14": 32.49999999999994,
      "macd": 0.0,
      "macd_signal": 0.0,
      "macd_histogram": 0.0,
      "volume_ma20": 132305.0,
      "volume_ratio": 0.4572767469105476,
      "poc": 0.0,
      "vah": 0.0,
      "val": 0.0,
      "rs_rating": 50
    },
    {
      "date": "2026-01-07",
      "symbol": "TDH",
      "open": 4.25,
      "high": 4.3,
      "low": 4.23,
      "close": 4.29,
      "volume": 193800,
      "change_pct": 0.4683840749414525,
      "ma20": 4.4185,
      "ma50": 4.662800000000001,
      "ma200": 4.662800000000001,
      "rsi_14": 30.769230769230745,
      "macd": 0.0,
      "macd_signal": 0.0,
      "macd_histogram": 0.0,
      "volume_ma20": 138300.0,
      "volume_ratio": 1.4013015184381779,
      "poc": 0.0,
      "vah": 0.0,
      "val": 0.0,
      "rs_rating": 50
    },
    {
      "date": "2026-01-08",
      "symbol": "TDH",
      "open": 4.29,
      "high": 4.33,
      "low": 4.2,
      "close": 4.2,
      "volume": 65000,
      "change_pct": -2.0979020979020935,
      "ma20": 4.398000000000001,
      "ma50": 4.648999999999999,
      "ma200": 4.648999999999999,
      "rsi_14": 26.66666666666667,
      "macd": 0.0,
      "macd_signal": 0.0,
      "macd_histogram": 0.0,
      "volume_ma20": 123050.0,
      "volume_ratio": 0.5282405526208859,
      "poc": 0.0,
      "vah": 0.0,
      "val": 0.0,
      "rs_rating": 50
    },
    {
      "date": "2026-01-09",
      "symbol": "TDH",
      "open": 4.2,
      "high": 4.26,
      "low": 4.15,
      "close": 4.2,
      "volume": 107900,
      "change_pct": 0.0,
      "ma20": 4.378500000000001,
      "ma50": 4.632999999999999,
      "ma200": 4.632999999999999,
      "rsi_14": 27.272727272727266,
      "macd": 0.0,
      "macd_signal": 0.0,
      "macd_histogram": 0.0,
      "volume_ma20": 119585.0,
      "volume_ratio": 0.9022870761383117,
      "poc": 0.0,
      "vah": 0.0,
      "val": 0.0,
      "rs_rating": 50
    },
    {
      "date": "2026-01-12",
      "symbol": "TDH",
      "open": 4.12,
      "high": 4.3,
      "low": 4.12,
      "close": 4.19,
      "volume": 113000,
      "change_pct": -0.23809523809523725,
      "ma20": 4.3585,
      "ma50": 4.6128,
      "ma200": 4.6128,
      "rsi_14": 17.500000000000043,
      "macd": 0.0,
      "macd_signal": 0.0,
      "macd_histogram": 0.0,
      "volume_ma20": 117660.0,
      "volume_ratio": 0.9603943566207717,
      "poc": 0.0,
      "vah": 0.0,
      "val": 0.0,
      "rs_rating": 50
    },
    {
      "date": "2026-01-13",
      "symbol": "TDH",
      "open": 4.2,
      "high": 4.23,
      "low": 4.17,
      "close": 4.2,
      "volume": 69800,
      "change_pct": 0.23866348448686736,
      "ma20": 4.347,
      "ma50": 4.593,
      "ma200": 4.593,
      "rsi_14": 20.0,
      "macd": 0.0,
      "macd_signal": 0.0,
      "macd_histogram": 0.0,
      "volume_ma20": 114335.0,
      "volume_ratio": 0.610486727598723,
      "poc": 0.0,
      "vah": 0.0,
      "val": 0.0,
      "rs_rating": 50
    },
    {
      "date": "2026-01-14",
      "symbol": "TDH",
      "open": 4.21,
      "high": 4.21,
      "low": 4.1,
      "close": 4.17,
      "volume": 172000,
      "change_pct": -0.7142857142857229,
      "ma20": 4.335,
      "ma50": 4.578399999999999,
      "ma200": 4.578399999999999,
      "rsi_14": 20.0,
      "macd": 0.0,
      "macd_signal": 0.0,
      "macd_histogram": 0.0,
      "volume_ma20": 114415.0,
      "volume_ratio": 1.503299392562164,
      "poc": 0.0,
      "vah": 0.0,
      "val": 0.0,
      "rs_rating": 50
    },
    {
      "date": "2026-01-15",
      "symbol": "TDH",
      "open": 4.19,
      "high": 4.19,
      "low": 4.12,
      "close": 4.18,
      "volume": 133700,
      "change_pct": 0.23980815347721673,
      "ma20": 4.322,
      "ma50": 4.5645999999999995,
      "ma200": 4.5645999999999995,
      "rsi_14": 17.948717948718,
      "macd": 0.0,
      "macd_signal": 0.0,
      "macd_histogram": 0.0,
      "volume_ma20": 113975.0,
      "volume_ratio": 1.1730642684799297,
      "poc": 0.0,
      "vah": 0.0,
      "val": 0.0,
      "rs_rating": 50
    },
    {
      "date": "2026-01-16",
      "symbol": "TDH",
      "open": 4.18,
      "high": 4.22,
      "low": 4.14,
      "close": 4.17,
      "volume": 162600,
      "change_pct": -0.23923444976076125,
      "ma20": 4.3100000000000005,
      "ma50": 4.5538,
      "ma200": 4.5538,
      "rsi_14": 20.000000000000057,
      "macd": 0.0,
      "macd_signal": 0.0,
      "macd_histogram": 0.0,
      "volume_ma20": 106680.0,
      "volume_ratio": 1.5241844769403825,
      "poc": 0.0,
      "vah": 0.0,
      "val": 0.0,
      "rs_rating": 50
    },
    {
      "date": "2026-01-19",
      "symbol": "TDH",
      "open": 4.18,
      "high": 4.18,
      "low": 4.16,
      "close": 4.17,
      "volume": 51400,
      "change_pct": 0.0,
      "ma20": 4.2985,
      "ma50": 4.5405999999999995,
      "ma200": 4.5405999999999995,
      "rsi_14": 20.000000000000057,
      "macd": 0.0,
      "macd_signal": 0.0,
      "macd_histogram": 0.0,
      "volume_ma20": 108605.0,
      "volume_ratio": 0.47327471110906494,
      "poc": 0.0,
      "vah": 0.0,
      "val": 0.0,
      "rs_rating": 50
    },
    {
      "date": "2026-01-20",
      "symbol": "TDH",
      "open": 4.2,
      "high": 4.45,
      "low": 4.2,
      "close": 4.22,
      "volume": 250800,
      "change_pct": 1.1990407673860837,
      "ma20": 4.287000000000001,
      "ma50": 4.5298,
      "ma200": 4.5298,
      "rsi_14": 32.43243243243245,
      "macd": 0.0,
      "macd_signal": 0.0,
      "macd_histogram": 0.0,
      "volume_ma20": 116240.0,
      "volume_ratio": 2.157604955264969,
      "poc": 0.0,
      "vah": 0.0,
      "val": 0.0,
      "rs_rating": 50
    },
    {
      "date": "2026-01-21",
      "symbol": "TDH",
      "open": 4.22,
      "high": 4.28,
      "low": 4.19,
      "close": 4.22,
      "volume": 75700,
      "change_pct": 0.0,
      "ma20": 4.276,
      "ma50": 4.5184,
      "ma200": 4.5184,
      "rsi_14": 26.470588235294088,
      "macd": 0.0,
      "macd_signal": 0.0,
      "macd_histogram": 0.0,
      "volume_ma20": 116860.0,
      "volume_ratio": 0.6477836727708369,
      "poc": 0.0,
      "vah": 0.0,
      "val": 0.0,
      "rs_rating": 50
    },
    {
      "date": "2026-01-22",
      "symbol": "TDH",
      "open": 4.2,
      "high": 4.28,
      "low": 4.17,
      "close": 4.2,
      "volume": 131400,
      "change_pct": -0.4739336492890933,
      "ma20": 4.2655,
      "ma50": 4.5064,
      "ma200": 4.5064,
      "rsi_14": 25.714285714285694,
      "macd": 0.0,
      "macd_signal": 0.0,
      "macd_histogram": 0.0,
      "volume_ma20": 120185.0,
      "volume_ratio": 1.09331447351999,
      "poc": 0.0,
      "vah": 0.0,
      "val": 0.0,
      "rs_rating": 50
    },
    {
      "date": "2026-01-23",
      "symbol": "TDH",
      "open": 4.23,
      "high": 4.23,
      "low": 4.11,
      "close": 4.11,
      "volume": 57400,
      "change_pct": -2.1428571428571352,
      "ma20": 4.249499999999999,
      "ma50": 4.492000000000001,
      "ma200": 4.492000000000001,
      "rsi_14": 21.951219512195124,
      "macd": 0.0,
      "macd_signal": 0.0,
      "macd_histogram": 0.0,
      "volume_ma20": 114680.0,
      "volume_ratio": 0.5005231949773282,
      "poc": 0.0,
      "vah": 0.0,
      "val": 0.0,
      "rs_rating": 50
    },
    {
      "date": "2026-01-26",
      "symbol": "TDH",
      "open": 4.11,
      "high": 4.2,
      "low": 4.0,
      "close": 4.05,
      "volume": 71900,
      "change_pct": -1.4598540145985495,
      "ma20": 4.233,
      "ma50": 4.4774,
      "ma200": 4.4774,
      "rsi_14": 22.5,
      "macd": 0.0,
      "macd_signal": 0.0,
      "macd_histogram": 0.0,
      "volume_ma20": 112365.0,
      "volume_ratio": 0.6398789658701552,
      "poc": 0.0,
      "vah": 0.0,
      "val": 0.0,
      "rs_rating": 50
    },
    {
      "date": "2026-01-27",
      "symbol": "TDH",
      "open": 4.05,
      "high": 4.1,
      "low": 3.95,
      "close": 4.05,
      "volume": 58500,
      "change_pct": 0.0,
      "ma20": 4.216499999999999,
      "ma50": 4.463800000000001,
      "ma200": 4.463800000000001,
      "rsi_14": 18.421052631578846,
      "macd": 0.0,
      "macd_signal": 0.0,
      "macd_histogram": 0.0,
      "volume_ma20": 109730.0,
      "volume_ratio": 0.5331267656976214,
      "poc": 0.0,
      "vah": 0.0,
      "val": 0.0,
      "rs_rating": 50
    },
    {
      "date": "2026-01-28",
      "symbol": "TDH",
      "open": 4.21,
      "high": 4.33,
      "low": 4.21,
      "close": 4.33,
      "volume": 239900,
      "change_pct": 6.913580246913598,
      "ma20": 4.2155000000000005,
      "ma50": 4.454000000000001,
      "ma200": 4.454000000000001,
      "rsi_14": 61.40350877192982,
      "macd": 0.0,
      "macd_signal": 0.0,
      "macd_histogram": 0.0,
      "volume_ma20": 116440.0,
      "volume_ratio": 2.060288560632085,
      "poc": 0.0,
      "vah": 0.0,
      "val": 0.0,
      "rs_rating": 50
    },
    {
      "date": "2026-01-29",
      "symbol": "TDH",
      "open": 4.63,
      "high": 4.63,
      "low": 4.4,
      "close": 4.4,
      "volume": 632700,
      "change_pct": 1.616628175519641,
      "ma20": 4.2165,
      "ma50": 4.446000000000001,
      "ma200": 4.446000000000001,
      "rsi_14": 65.62500000000003,
      "macd": 0.0,
      "macd_signal": 0.0,
      "macd_histogram": 0.0,
      "volume_ma20": 143480.0,
      "volume_ratio": 4.409673822135489,
      "poc": 0.0,
      "vah": 0.0,
      "val": 0.0,
      "rs_rating": 50
    },
    {
      "date": "2026-01-30",
      "symbol": "TDH",
      "open": 4.24,
      "high": 4.56,
      "low": 4.24,
      "close": 4.27,
      "volume": 129100,
      "change_pct": -2.9545454545454763,
      "ma20": 4.2115,
      "ma50": 4.4362,
      "ma200": 4.4362,
      "rsi_14": 55.26315789473679,
      "macd": 0.0,
      "macd_signal": 0.0,
      "macd_histogram": 0.0,
      "volume_ma20": 148380.0,
      "volume_ratio": 0.8700633508559105,
      "poc": 0.0,
      "vah": 0.0,
      "val": 0.0,
      "rs_rating": 50
    },
    {
      "date": "2026-02-02",
      "symbol": "TDH",
      "open": 4.25,
      "high": 4.26,
      "low": 4.05,
      "close": 4.1,
      "volume": 305900,
      "change_pct": -3.9812646370023352,
      "ma20": 4.1995,
      "ma50": 4.4234,
      "ma200": 4.4234,
      "rsi_14": 44.56521739130433,
      "macd": 0.0,
      "macd_signal": 0.0,
      "macd_histogram": 0.0,
      "volume_ma20": 154150.0,
      "volume_ratio": 1.9844307492701914,
      "poc": 0.0,
      "vah": 0.0,
      "val": 0.0,
      "rs_rating": 50
    },
    {
      "date": "2026-02-03",
      "symbol": "TDH",
      "open": 4.12,
      "high": 4.32,
      "low": 4.05,
      "close": 4.28,
      "volume": 178400,
      "change_pct": 4.3902439024390505,
      "ma20": 4.200000000000001,
      "ma50": 4.4118,
      "ma200": 4.4118,
      "rsi_14": 55.14018691588786,
      "macd": 0.0,
      "macd_signal": 0.0,
      "macd_histogram": 0.0,
      "volume_ma20": 160045.0,
      "volume_ratio": 1.1146864944234434,
      "poc": 0.0,
      "vah": 0.0,
      "val": 0.0,
      "rs_rating": 50
    },
    {
      "date": "2026-02-04",
      "symbol": "TDH",
      "open": 4.28,
      "high": 4.28,
      "low": 4.11,
      "close": 4.19,
      "volume": 202400,
      "change_pct": -2.102803738317749,
      "ma20": 4.194999999999999,
      "ma50": 4.3986,
      "ma200": 4.3986,
      "rsi_14": 50.43478260869568,
      "macd": 0.0,
      "macd_signal": 0.0,
      "macd_histogram": 0.0,
      "volume_ma20": 160475.0,
      "volume_ratio": 1.2612556472970868,
      "poc": 0.0,
      "vah": 0.0,
      "val": 0.0,
      "rs_rating": 50
    },
    {
      "date": "2026-02-05",
      "symbol": "TDH",
      "open": 4.18,
      "high": 4.19,
      "low": 4.1,
      "close": 4.12,
      "volume": 112900,
      "change_pct": -1.670644391408116,
      "ma20": 4.191,
      "ma50": 4.384399999999999,
      "ma200": 4.384399999999999,
      "rsi_14": 47.93388429752067,
      "macd": 0.0,
      "macd_signal": 0.0,
      "macd_histogram": 0.0,
      "volume_ma20": 162870.0,
      "volume_ratio": 0.6931908884386321,
      "poc": 0.0,
      "vah": 0.0,
      "val": 0.0,
      "rs_rating": 50
    },
    {
      "date": "2026-02-06",
      "symbol": "TDH",
      "open": 4.12,
      "high": 4.12,
      "low": 4.01,
      "close": 4.07,
      "volume": 62500,
      "change_pct": -1.2135922330097082,
      "ma20": 4.1845,
      "ma50": 4.369800000000001,
      "ma200": 4.369800000000001,
      "rsi_14": 46.031746031746046,
      "macd": 0.0,
      "macd_signal": 0.0,
      "macd_histogram": 0.0,
      "volume_ma20": 160600.0,
      "volume_ratio": 0.3891656288916563,
      "poc": 0.0,
      "vah": 0.0,
      "val": 0.0,
      "rs_rating": 50
    },
    {
      "date": "2026-02-08",
      "symbol": "TDH",
      "open": 4.12,
      "high": 4.12,
      "low": 4.01,
      "close": 4.07,
      "volume": 62500,
      "change_pct": -1.2135922330097082,
      "ma20": 4.1845,
      "ma50": 4.369800000000001,
      "ma200": 4.369800000000001,
      "rsi_14": 40.76918945332142,
      "macd": -0.05630593081352231,
      "macd_signal": -0.06107924901270529,
      "macd_histogram": 0,
      "volume_ma20": 160600.0,
      "volume_ratio": 0.3891656288916563,
      "poc": 4.174399999999997,
      "vah": 4.3307999999999955,
      "val": 4.058799999999999,
      "rs_rating": 50
    },
    {
      "date": "2026-02-09",
      "symbol": "TDH",
      "open": 4.1,
      "high": 4.1,
      "low": 4.01,
      "close": 4.02,
      "volume": 53600,
      "change_pct": -1.2285012285012442,
      "ma20": 4.176,
      "ma50": 4.3544,
      "ma200": 4.3544,
      "rsi_14": 38.6857842766532,
      "macd": -0.06491403958953779,
      "macd_signal": -0.06184626378786649,
      "macd_histogram": 0,
      "volume_ma20": 157630.0,
      "volume_ratio": 0.3400367950263275,
      "poc": 4.174399999999997,
      "vah": 4.3307999999999955,
      "val": 4.0451999999999995,
      "rs_rating": 50
    },
    {
      "date": "2026-02-10",
      "symbol": "TDH",
      "open": 3.91,
      "high": 4.02,
      "low": 3.91,
      "close": 3.97,
      "volume": 120100,
      "change_pct": -1.243781094527352,
      "ma20": 4.1645,
      "ma50": 4.3382,
      "ma200": 4.3382,
      "rsi_14": 36.66787311298042,
      "macd": -0.07490692894179674,
      "macd_signal": -0.06445819284339209,
      "macd_histogram": 0,
      "volume_ma20": 160145.0,
      "volume_ratio": 0.7499453620156733,
      "poc": 4.176400000000004,
      "vah": 4.342000000000006,
      "val": 3.9964000000000013,
      "rs_rating": 50
    },
    {
      "date": "2026-02-11",
      "symbol": "TDH",
      "open": 3.98,
      "high": 4.03,
      "low": 3.96,
      "close": 4.0,
      "volume": 83800,
      "change_pct": 0.7556675062972307,
      "ma20": 4.156,
      "ma50": 4.322399999999999,
      "ma200": 4.322399999999999,
      "rsi_14": 38.732890335726665,
      "macd": -0.0794893597987425,
      "macd_signal": -0.067464312914875,
      "macd_histogram": 0,
      "volume_ma20": 155735.0,
      "volume_ratio": 0.5380935563617684,
      "poc": 4.176400000000004,
      "vah": 4.327600000000006,
      "val": 3.967600000000001,
      "rs_rating": 50
    }
  ]
}