{
  "timestamp": "2026-02-11T17:27:20.700083",
  "data": [
    {
      "period": "Q1",
      "revenue": 0.0,
      "profit": 11053113000000.0,
      "eps": 0.0,
      "roe": 21.08248688,
      "roa": 1.34252175,
      "gross_margin": 0.0,
      "net_margin": 0.0,
      "operating_cash_flow": -2378836000000.0,
      "investing_cash_flow": -760506000000.0,
      "financing_cash_flow": -2416496000000.0,
      "pe": 8.3303894532,
      "pb": 1.6148964776
    },
    {
      "period": "Q2",
      "revenue": 0.0,
      "profit": 8448784000000.0,
      "eps": 0.0,
      "roe": 20.95951299,
      "roa": 1.30388701,
      "gross_margin": 0.0,
      "net_margin": 0.0,
      "operating_cash_flow": 66767196000000.0,
      "investing_cash_flow": -572769000000.0,
      "financing_cash_flow": 0.0,
      "pe": 9.6574823913,
      "pb": 1.908187043
    },
    {
      "period": "Q3",
      "revenue": 0.0,
      "profit": 9669885000000.0,
      "eps": 0.0,
      "roe": 19.83396542,
      "roa": 1.24243001,
      "gross_margin": 0.0,
      "net_margin": 0.0,
      "operating_cash_flow": 27016581000000.0,
      "investing_cash_flow": -358420000000.0,
      "financing_cash_flow": 0.0,
      "pe": 9.7010862292,
      "pb": 1.7952342733
    },
    {
      "period": "Q4",
      "revenue": 0.0,
      "profit": 5418875000000.0,
      "eps": 0.0,
      "roe": 17.81584051,
      "roa": 1.11645876,
      "gross_margin": 0.0,
      "net_margin": 0.0,
      "operating_cash_flow": -8760941000000.0,
      "investing_cash_flow": -223497000000.0,
      "financing_cash_flow": 0.0,
      "pe": 9.2176089344,
      "pb": 1.5555429688
    },
    {
      "period": "Q5",
      "revenue": 0.0,
      "profit": 9798251000000.0,
      "eps": 0.0,
      "roe": 18.47695587,
      "roa": 1.14749694,
      "gross_margin": 0.0,
      "net_margin": 0.0,
      "operating_cash_flow": 1670206000000.0,
      "investing_cash_flow": -722655000000.0,
      "financing_cash_flow": 0.0,
      "pe": 7.9972963254,
      "pb": 1.3740372886
    },
    {
      "period": "Q6",
      "revenue": 0.0,
      "profit": 5225859000000.0,
      "eps": 0.0,
      "roe": 16.19806236,
      "roa": 1.01955449,
      "gross_margin": 0.0,
      "net_margin": 0.0,
      "operating_cash_flow": 16134027000000.0,
      "investing_cash_flow": -178693000000.0,
      "financing_cash_flow": 0.0,
      "pe": 9.1567296577,
      "pb": 1.4163316712
    },
    {
      "period": "Q7",
      "revenue": 0.0,
      "profit": 5365295000000.0,
      "eps": 0.0,
      "roe": 15.73759619,
      "roa": 0.9954145500000001,
      "gross_margin": 0.0,
      "net_margin": 0.0,
      "operating_cash_flow": 48014597000000.0,
      "investing_cash_flow": -226586000000.0,
      "financing_cash_flow": 1537000000.0,
      "pe": 9.5332393341,
      "pb": 1.433469585
    },
    {
      "period": "Q8",
      "revenue": 0.0,
      "profit": 4958810000000.0,
      "eps": 0.0,
      "roe": 16.17335633,
      "roa": 1.02533718,
      "gross_margin": 0.0,
      "net_margin": 0.0,
      "operating_cash_flow": 36369856000000.0,
      "investing_cash_flow": -201089000000.0,
      "financing_cash_flow": 0.0,
      "pe": 8.5302846743,
      "pb": 1.3250765449
    },
    {
      "period": "Q9",
      "revenue": 0.0,
      "profit": 6119475000000.0,
      "eps": 0.0,
      "roe": 16.99791545,
      "roa": 1.03625882,
      "gross_margin": 0.0,
      "net_margin": 0.0,
      "operating_cash_flow": 7141948000000.0,
      "investing_cash_flow": -344232000000.0,
      "financing_cash_flow": 0.0,
      "pe": 9.6858451598,
      "pb": 1.5421308573
    },
    {
      "period": "Q10",
      "revenue": 0.0,
      "profit": 3863075000000.0,
      "eps": 0.0,
      "roe": 15.72301237,
      "roa": 0.98261541,
      "gross_margin": 0.0,
      "net_margin": 0.0,
      "operating_cash_flow": 19183597000000.0,
      "investing_cash_flow": -125315000000.0,
      "financing_cash_flow": 0.0,
      "pe": 9.3284709241,
      "pb": 1.3960398892
    },
    {
      "period": "Q11",
      "revenue": 0.0,
      "profit": 5203306000000.0,
      "eps": 0.0,
      "roe": 15.812908749999998,
      "roa": 0.97229779,
      "gross_margin": 0.0,
      "net_margin": 0.0,
      "operating_cash_flow": 14831974000000.0,
      "investing_cash_flow": -239563000000.0,
      "financing_cash_flow": 0.0,
      "pe": 8.0785329747,
      "pb": 1.213171552
    },
    {
      "period": "Q12",
      "revenue": 0.0,
      "profit": 4806377000000.0,
      "eps": 0.0,
      "roe": 15.85577156,
      "roa": 0.9639872,
      "gross_margin": 0.0,
      "net_margin": 0.0,
      "operating_cash_flow": -12354419000000.0,
      "investing_cash_flow": -29524000000.0,
      "financing_cash_flow": 0.0,
      "pe": 8.4556038115,
      "pb": 1.285115942
    },
    {
      "period": "Q13",
      "revenue": 0.0,
      "profit": 4260411000000.0,
      "eps": 0.0,
      "roe": 16.62403072,
      "roa": 1.00449029,
      "gross_margin": 0.0,
      "net_margin": 0.0,
      "operating_cash_flow": 38532149000000.0,
      "investing_cash_flow": -243427000000.0,
      "financing_cash_flow": 0.0,
      "pe": 8.3366155321,
      "pb": 1.3017748571
    },
    {
      "period": "Q14",
      "revenue": 0.0,
      "profit": 3338328000000.0,
      "eps": 0.0,
      "roe": 15.53582796,
      "roa": 0.93827613,
      "gross_margin": 0.0,
      "net_margin": 0.0,
      "operating_cash_flow": 20511712000000.0,
      "investing_cash_flow": -138696000000.0,
      "financing_cash_flow": 0.0,
      "pe": 8.9827321732,
      "pb": 1.3270975177
    },
    {
      "period": "Q15",
      "revenue": 0.0,
      "profit": 4645413000000.0,
      "eps": 0.0,
      "roe": 15.05372438,
      "roa": 0.92767585,
      "gross_margin": 0.0,
      "net_margin": 0.0,
      "operating_cash_flow": 9974925000000.0,
      "investing_cash_flow": -116868000000.0,
      "financing_cash_flow": 0.0,
      "pe": 7.328079565,
      "pb": 1.055038073
    },
    {
      "period": "Q16",
      "revenue": 0.0,
      "profit": 4663907000000.0,
      "eps": 0.0,
      "roe": 12.91465057,
      "roa": 0.80409727,
      "gross_margin": 0.0,
      "net_margin": 0.0,
      "operating_cash_flow": 16376396000000.0,
      "investing_cash_flow": -14340000000.0,
      "financing_cash_flow": -3844600000000.0,
      "pe": 10.3778688065,
      "pb": 1.3076787033
    },
    {
      "period": "Q17",
      "revenue": 0.0,
      "profit": 2920816000000.0,
      "eps": 0.0,
      "roe": 15.736289649999998,
      "roa": 0.9807617799999999,
      "gross_margin": 0.0,
      "net_margin": 0.0,
      "operating_cash_flow": 32546722000000.0,
      "investing_cash_flow": -197692000000.0,
      "financing_cash_flow": 0.0,
      "pe": 9.6191693531,
      "pb": 1.4579371491
    },
    {
      "period": "Q18",
      "revenue": 0.0,
      "profit": 2459772000000.0,
      "eps": 0.0,
      "roe": 18.05922508,
      "roa": 1.1792542799999999,
      "gross_margin": 0.0,
      "net_margin": 0.0,
      "operating_cash_flow": -53734155000000.0,
      "investing_cash_flow": -243923000000.0,
      "financing_cash_flow": 0.0,
      "pe": 10.0460008753,
      "pb": 1.7483106177
    },
    {
      "period": "Q19",
      "revenue": 0.0,
      "profit": 2250195000000.0,
      "eps": 0.0,
      "roe": 18.54677754,
      "roa": 1.21077068,
      "gross_margin": 0.0,
      "net_margin": 0.0,
      "operating_cash_flow": 37158105000000.0,
      "investing_cash_flow": -88480000000.0,
      "financing_cash_flow": -21267000000.0,
      "pe": 8.9935429584,
      "pb": 1.5928715041
    },
    {
      "period": "Q20",
      "revenue": 0.0,
      "profit": 6461533000000.0,
      "eps": 0.0,
      "roe": 20.75822204351425,
      "roa": 1.3671962544322014,
      "gross_margin": 0.0,
      "net_margin": 0.0,
      "operating_cash_flow": -10701222000000.0,
      "investing_cash_flow": -44099000000.0,
      "financing_cash_flow": 0.0,
      "pe": 9.4889223724,
      "pb": 1.843626227
    }
  ]
}